[
  {
    "keyword": "Feature",
    "name": "HBC End to end - Place Order Registered/Guest users using split cards",
    "line": 1,
    "id": "hbc-end-to-end---place-order-registered/guest-users-using-split-cards",
    "tags": [],
    "uri": "sfcc/common_features/HBC_End2End/End_to_end_Gift_Cards_Flow.feature",
    "elements": [
      {
        "id": "hbc-end-to-end---place-order-registered/guest-users-using-split-cards;sfdev-4582-verify-for-bay-order-for-multiple-quantities-of-bopis-item-for-the-guest-user-using-mastercard-and-gc.",
        "keyword": "Scenario",
        "line": 141,
        "name": "SFDEV-4582 Verify for Bay order for multiple quantities of BOPIS item for the guest user using Mastercard and GC.",
        "tags": [],
        "type": "scenario",
        "steps": [
          {
            "arguments": [],
            "keyword": "Given ",
            "line": 142,
            "name": "I am on the website",
            "match": {
              "location": "utility/helper.js:10"
            },
            "result": {
              "status": "passed",
              "duration": 40938000000
            }
          },
          {
            "arguments": [],
            "keyword": "And ",
            "line": 143,
            "name": "Wait for \"3000\" mili seconds",
            "match": {
              "location": "utility/helper.js:10"
            },
            "result": {
              "status": "passed",
              "duration": 3004000000
            }
          },
          {
            "arguments": [],
            "keyword": "And ",
            "line": 150,
            "name": "I add \"BOPIS Item2 SFDEV-4582\" to bag",
            "match": {
              "location": "utility/helper.js:10"
            },
            "result": {
              "status": "passed",
              "duration": 31056000000
            }
          },
          {
            "arguments": [],
            "keyword": "And ",
            "line": 151,
            "name": "I click on \"minicart link\"",
            "match": {
              "location": "utility/helper.js:10"
            },
            "result": {
              "status": "passed",
              "duration": 16544000000
            }
          },
          {
            "arguments": [],
            "keyword": "And ",
            "line": 152,
            "name": "I am adding quantity",
            "match": {
              "location": "utility/helper.js:10"
            },
            "result": {
              "status": "passed",
              "duration": 2402000000
            }
          },
          {
            "arguments": [],
            "keyword": "And ",
            "line": 153,
            "name": "Select BOPIS \"In Stock\" SFDEV2580 store in \"PDP\"",
            "match": {
              "location": "utility/helper.js:10"
            },
            "result": {
              "status": "failed",
              "duration": 60007000000,
              "error_message": "Error: function timed out, ensure the promise resolves within 60000 milliseconds\n    at Timeout._onTimeout (/Users/375919/PycharmProjects/Sfcc-TestAutomation-HBC/node_modules/cucumber/lib/user_code_runner.js:76:18)\n    at listOnTimeout (internal/timers.js:536:17)\n    at processTimers (internal/timers.js:480:7)"
            }
          },
          {
            "arguments": [],
            "keyword": "And ",
            "line": 154,
            "name": "Wait for \"3000\" mili seconds",
            "match": {
              "location": "utility/helper.js:10"
            },
            "result": {
              "status": "skipped"
            }
          },
          {
            "arguments": [],
            "keyword": "And ",
            "line": 155,
            "name": "Wait for \"4000\" mili seconds",
            "match": {
              "location": "utility/helper.js:10"
            },
            "result": {
              "status": "skipped"
            }
          },
          {
            "arguments": [],
            "keyword": "And ",
            "line": 156,
            "name": "I click on \"checkout button in cart page\"",
            "match": {
              "location": "utility/helper.js:10"
            },
            "result": {
              "status": "skipped"
            }
          },
          {
            "arguments": [],
            "keyword": "And ",
            "line": 157,
            "name": "I click on \"checkout as guest button in cart page\"",
            "match": {
              "location": "utility/helper.js:10"
            },
            "result": {
              "status": "skipped"
            }
          },
          {
            "arguments": [],
            "keyword": "And ",
            "line": 158,
            "name": "I enter my \"In-Store Pickup Person details\" in the textbox",
            "match": {
              "location": "utility/helper.js:10"
            },
            "result": {
              "status": "skipped"
            }
          },
          {
            "arguments": [],
            "keyword": "And ",
            "line": 159,
            "name": "I click on - \"checkout shipping instore pickup save and continue button\"",
            "match": {
              "location": "utility/helper.js:10"
            },
            "result": {
              "status": "skipped"
            }
          },
          {
            "arguments": [],
            "keyword": "And ",
            "line": 160,
            "name": "Wait for \"2000\" mili seconds",
            "match": {
              "location": "utility/helper.js:10"
            },
            "result": {
              "status": "skipped"
            }
          },
          {
            "arguments": [],
            "keyword": "And ",
            "line": 161,
            "name": "I enter my \"Master Card Details\" in the textbox",
            "match": {
              "location": "utility/helper.js:10"
            },
            "result": {
              "status": "skipped"
            }
          },
          {
            "arguments": [],
            "keyword": "And ",
            "line": 162,
            "name": "I click on - \"add gift card button\"",
            "match": {
              "location": "utility/helper.js:10"
            },
            "result": {
              "status": "skipped"
            }
          },
          {
            "arguments": [],
            "keyword": "And ",
            "line": 163,
            "name": "I enter my \"Gift Card Number-1\" in the textbox",
            "match": {
              "location": "utility/helper.js:10"
            },
            "result": {
              "status": "skipped"
            }
          },
          {
            "arguments": [],
            "keyword": "And ",
            "line": 164,
            "name": "Wait for \"3000\" mili seconds",
            "match": {
              "location": "utility/helper.js:10"
            },
            "result": {
              "status": "skipped"
            }
          },
          {
            "arguments": [],
            "keyword": "And ",
            "line": 165,
            "name": "I click on - \"checkout payment section save and continue button\"",
            "match": {
              "location": "utility/helper.js:10"
            },
            "result": {
              "status": "skipped"
            }
          },
          {
            "keyword": "After",
            "hidden": true,
            "match": {
              "location": "cucumber.conf.js:38"
            },
            "result": {
              "status": "passed",
              "duration": 1000000
            }
          }
        ]
      }
    ]
  }
]