[
  {
    "keyword": "Feature",
    "name": "HBC End to end - Place Order Registered/Guest users using Amex Card",
    "line": 1,
    "id": "hbc-end-to-end---place-order-registered/guest-users-using-amex-card",
    "tags": [],
    "uri": "sfcc/common_features/HBC_End2End/End_to_end_Amex_Card.feature",
    "elements": [
      {
        "id": "hbc-end-to-end---place-order-registered/guest-users-using-amex-card;sfdev-3310-verify-for-bay-website-order-for-a-registered-user,-multiple-items-multiple-quantities,-shipment-paid-by-amex.",
        "keyword": "Scenario",
        "line": 6,
        "name": "SFDEV-3310 Verify for Bay website order for a registered user, multiple items multiple quantities, shipment paid by Amex.",
        "tags": [],
        "type": "scenario",
        "steps": [
          {
            "arguments": [],
            "keyword": "Given ",
            "line": 7,
            "name": "I am on the website",
            "match": {
              "location": "utility/helper.js:10"
            },
            "result": {
              "status": "passed",
              "duration": 38511000000
            }
          },
          {
            "arguments": [],
            "keyword": "And ",
            "line": 8,
            "name": "Wait for \"3000\" mili seconds",
            "match": {
              "location": "utility/helper.js:10"
            },
            "result": {
              "status": "passed",
              "duration": 3006000000
            }
          },
          {
            "arguments": [],
            "keyword": "And ",
            "line": 9,
            "name": "I login to the application with valid credentials",
            "match": {
              "location": "utility/helper.js:10"
            },
            "result": {
              "status": "passed",
              "duration": 37450000000
            }
          },
          {
            "arguments": [],
            "keyword": "And ",
            "line": 10,
            "name": "Wait for \"3000\" mili seconds",
            "match": {
              "location": "utility/helper.js:10"
            },
            "result": {
              "status": "passed",
              "duration": 3005000000
            }
          },
          {
            "arguments": [],
            "keyword": "And ",
            "line": 11,
            "name": "Remove saved addresses from my account page",
            "match": {
              "location": "utility/helper.js:10"
            },
            "result": {
              "status": "passed",
              "duration": 16135000000
            }
          },
          {
            "arguments": [],
            "keyword": "And ",
            "line": 12,
            "name": "Remove saved credit cards from my account page",
            "match": {
              "location": "utility/helper.js:10"
            },
            "result": {
              "status": "passed",
              "duration": 15820000000
            }
          },
          {
            "arguments": [],
            "keyword": "And ",
            "line": 13,
            "name": "Wait for \"3000\" mili seconds",
            "match": {
              "location": "utility/helper.js:10"
            },
            "result": {
              "status": "passed",
              "duration": 3001000000
            }
          },
          {
            "arguments": [],
            "keyword": "And ",
            "line": 14,
            "name": "Remove products from cart page",
            "match": {
              "location": "utility/helper.js:10"
            },
            "result": {
              "status": "passed",
              "duration": 14985000000
            }
          },
          {
            "arguments": [],
            "keyword": "And ",
            "line": 15,
            "name": "Wait for \"3000\" mili seconds",
            "match": {
              "location": "utility/helper.js:10"
            },
            "result": {
              "status": "passed",
              "duration": 3006000000
            }
          },
          {
            "arguments": [],
            "keyword": "And ",
            "line": 16,
            "name": "Click on Start Shopping button",
            "match": {
              "location": "utility/helper.js:10"
            },
            "result": {
              "status": "passed",
              "duration": 1000000
            }
          },
          {
            "arguments": [],
            "keyword": "And ",
            "line": 17,
            "name": "I add \"Product2 SFDEV-4585\" to bag",
            "match": {
              "location": "utility/helper.js:10"
            },
            "result": {
              "status": "passed",
              "duration": 28204000000
            }
          },
          {
            "arguments": [],
            "keyword": "And ",
            "line": 18,
            "name": "I click on \"minicart link\"",
            "match": {
              "location": "utility/helper.js:10"
            },
            "result": {
              "status": "passed",
              "duration": 9004000000
            }
          },
          {
            "arguments": [],
            "keyword": "And ",
            "line": 19,
            "name": "I am adding quantity",
            "match": {
              "location": "utility/helper.js:10"
            },
            "result": {
              "status": "passed",
              "duration": 2138000000
            }
          },
          {
            "arguments": [],
            "keyword": "And ",
            "line": 20,
            "name": "Wait for \"1000\" mili seconds",
            "match": {
              "location": "utility/helper.js:10"
            },
            "result": {
              "status": "passed",
              "duration": 1005000000
            }
          },
          {
            "arguments": [],
            "keyword": "And ",
            "line": 21,
            "name": "I am adding quantity",
            "match": {
              "location": "utility/helper.js:10"
            },
            "result": {
              "status": "passed",
              "duration": 2108000000
            }
          },
          {
            "arguments": [],
            "keyword": "And ",
            "line": 22,
            "name": "Wait for \"2000\" mili seconds",
            "match": {
              "location": "utility/helper.js:10"
            },
            "result": {
              "status": "passed",
              "duration": 2005000000
            }
          },
          {
            "arguments": [],
            "keyword": "And ",
            "line": 23,
            "name": "click on home logo",
            "match": {
              "location": "utility/helper.js:10"
            },
            "result": {
              "status": "passed",
              "duration": 0
            }
          },
          {
            "arguments": [],
            "keyword": "And ",
            "line": 24,
            "name": "Wait for \"3000\" mili seconds",
            "match": {
              "location": "utility/helper.js:10"
            },
            "result": {
              "status": "passed",
              "duration": 15183000000
            }
          },
          {
            "arguments": [],
            "keyword": "And ",
            "line": 25,
            "name": "I add \"Product1 SFDEV-4585\" to bag",
            "match": {
              "location": "utility/helper.js:10"
            },
            "result": {
              "status": "passed",
              "duration": 23274000000
            }
          },
          {
            "arguments": [],
            "keyword": "And ",
            "line": 26,
            "name": "I click on \"minicart link\"",
            "match": {
              "location": "utility/helper.js:10"
            },
            "result": {
              "status": "passed",
              "duration": 11739000000
            }
          },
          {
            "arguments": [],
            "keyword": "And ",
            "line": 27,
            "name": "I am adding quantity",
            "match": {
              "location": "utility/helper.js:10"
            },
            "result": {
              "status": "passed",
              "duration": 2128000000
            }
          },
          {
            "arguments": [],
            "keyword": "And ",
            "line": 28,
            "name": "Wait for \"1000\" mili seconds",
            "match": {
              "location": "utility/helper.js:10"
            },
            "result": {
              "status": "passed",
              "duration": 1001000000
            }
          },
          {
            "arguments": [],
            "keyword": "And ",
            "line": 29,
            "name": "I am adding quantity",
            "match": {
              "location": "utility/helper.js:10"
            },
            "result": {
              "status": "passed",
              "duration": 2103000000
            }
          },
          {
            "arguments": [],
            "keyword": "And ",
            "line": 30,
            "name": "Wait for \"4000\" mili seconds",
            "match": {
              "location": "utility/helper.js:10"
            },
            "result": {
              "status": "passed",
              "duration": 4006000000
            }
          },
          {
            "arguments": [],
            "keyword": "And ",
            "line": 31,
            "name": "I click on \"checkout button in cart page\"",
            "match": {
              "location": "utility/helper.js:10"
            },
            "result": {
              "status": "passed",
              "duration": 1322000000
            }
          },
          {
            "arguments": [],
            "keyword": "And ",
            "line": 32,
            "name": "Wait for \"9000\" mili seconds",
            "match": {
              "location": "utility/helper.js:10"
            },
            "result": {
              "status": "passed",
              "duration": 9000000000
            }
          },
          {
            "arguments": [],
            "keyword": "When ",
            "line": 33,
            "name": "I click on - \"Add_new_shipping_address_in_checout_page\"",
            "match": {
              "location": "utility/helper.js:10"
            },
            "result": {
              "status": "passed",
              "duration": 2482000000
            }
          },
          {
            "arguments": [],
            "keyword": "And ",
            "line": 34,
            "name": "Wait for \"3000\" mili seconds",
            "match": {
              "location": "utility/helper.js:10"
            },
            "result": {
              "status": "passed",
              "duration": 3004000000
            }
          },
          {
            "arguments": [],
            "keyword": "And ",
            "line": 35,
            "name": "I enter my \"Shipping address-SFDEV-3310\" in the textbox",
            "match": {
              "location": "utility/helper.js:10"
            },
            "result": {
              "status": "passed",
              "duration": 6264000000
            }
          },
          {
            "arguments": [],
            "keyword": "And ",
            "line": 36,
            "name": "I click on - \"checkout save shipping address button\"",
            "match": {
              "location": "utility/helper.js:10"
            },
            "result": {
              "status": "passed",
              "duration": 2348000000
            }
          },
          {
            "arguments": [],
            "keyword": "And ",
            "line": 37,
            "name": "Wait for \"6000\" mili seconds",
            "match": {
              "location": "utility/helper.js:10"
            },
            "result": {
              "status": "passed",
              "duration": 6002000000
            }
          },
          {
            "arguments": [],
            "keyword": "And ",
            "line": 38,
            "name": "Select \"Standard\" shipping method",
            "match": {
              "location": "utility/helper.js:10"
            },
            "result": {
              "status": "passed",
              "duration": 4235000000
            }
          },
          {
            "arguments": [],
            "keyword": "And ",
            "line": 39,
            "name": "Wait for \"10000\" mili seconds",
            "match": {
              "location": "utility/helper.js:10"
            },
            "result": {
              "status": "passed",
              "duration": 10005000000
            }
          },
          {
            "arguments": [],
            "keyword": "And ",
            "line": 40,
            "name": "Refresh current page",
            "match": {
              "location": "utility/helper.js:10"
            },
            "result": {
              "status": "passed",
              "duration": 1000000
            }
          },
          {
            "arguments": [],
            "keyword": "And ",
            "line": 41,
            "name": "Wait for \"3000\" mili seconds",
            "match": {
              "location": "utility/helper.js:10"
            },
            "result": {
              "status": "passed",
              "duration": 6004000000
            }
          },
          {
            "arguments": [],
            "keyword": "And ",
            "line": 42,
            "name": "I click on - \"checkout shipping save and continue button\"",
            "match": {
              "location": "utility/helper.js:10"
            },
            "result": {
              "status": "passed",
              "duration": 5485000000
            }
          },
          {
            "arguments": [],
            "keyword": "And ",
            "line": 43,
            "name": "I enter my \"Amex Card Details\" in the textbox",
            "match": {
              "location": "utility/helper.js:10"
            },
            "result": {
              "status": "passed",
              "duration": 5699000000
            }
          },
          {
            "arguments": [],
            "keyword": "And ",
            "line": 44,
            "name": "I click on - \"checkout payment section save and continue button\"",
            "match": {
              "location": "utility/helper.js:10"
            },
            "result": {
              "status": "passed",
              "duration": 2360000000
            }
          },
          {
            "keyword": "After",
            "hidden": true,
            "match": {
              "location": "cucumber.conf.js:38"
            },
            "result": {
              "status": "passed",
              "duration": 1000000
            }
          }
        ]
      }
    ]
  }
]